Products.contentmigration-2.2.1-py2.7-nspkg.pth
Products/contentmigration/__init__.py
Products/contentmigration/archetypes.py
Products/contentmigration/archetypes.txt
Products/contentmigration/bugfixes.txt
Products/contentmigration/catalogpatch.py
Products/contentmigration/common.py
Products/contentmigration/configure.zcml
Products/contentmigration/field.py
Products/contentmigration/inplace.py
Products/contentmigration/inplace.txt
Products/contentmigration/migrator.py
Products/contentmigration/schemaextender.txt
Products/contentmigration/testcontent.py
Products/contentmigration/testing-schemaextender.zcml
Products/contentmigration/testing.zcml
Products/contentmigration/translocate.py
Products/contentmigration/translocate.txt
Products/contentmigration/utils.py
Products/contentmigration/walker.py
Products/contentmigration/basemigrator/__init__.py
Products/contentmigration/basemigrator/migrator.py
Products/contentmigration/basemigrator/walker.py
Products/contentmigration/profiles/testing/factorytool.xml
Products/contentmigration/profiles/testing/types.xml
Products/contentmigration/profiles/testing/types/CMF_Document.xml
Products/contentmigration/tests/__init__.py
Products/contentmigration/tests/cmtc.py
Products/contentmigration/tests/extensions.py
Products/contentmigration/tests/layer.py
Products/contentmigration/tests/testATFieldMigration.py
Products/contentmigration/tests/test_doctests.py
Products/contentmigration/tests/utils.py
Products.contentmigration-2.2.1.dist-info/METADATA
Products.contentmigration-2.2.1.dist-info/WHEEL
Products.contentmigration-2.2.1.dist-info/namespace_packages.txt
Products.contentmigration-2.2.1.dist-info/top_level.txt
Products.contentmigration-2.2.1.dist-info/RECORD
