Metadata-Version: 2.1
Name: Products.contentmigration
Version: 2.2.1
Summary: A generic content migration framework for Plone.
Home-page: https://pypi.org/project/Products.contentmigration
Author: Martin Aspeli (and others)
Author-email: plone-developers@lists.sourceforge.net
License: LGPL
Keywords: Plone Archetypes ATContentTypes
Platform: UNKNOWN
Classifier: Development Status :: 5 - Production/Stable
Classifier: Framework :: Plone
Classifier: Framework :: Plone :: 5.2
Classifier: Framework :: Plone :: 6.0
Classifier: Framework :: Plone :: Core
Classifier: License :: OSI Approved :: GNU Library or Lesser General Public License (LGPL)
Classifier: Programming Language :: Python
Classifier: Programming Language :: Python :: 2.7
Classifier: Programming Language :: Python :: 3.6
Classifier: Programming Language :: Python :: 3.7
Classifier: Programming Language :: Python :: 3.8
Requires-Dist: setuptools
Provides-Extra: test
Requires-Dist: archetypes.schemaextender ; extra == 'test'
Requires-Dist: plone.app.testing ; extra == 'test'
Requires-Dist: Products.CMFPlone ; extra == 'test'
Requires-Dist: six ; extra == 'test'
Requires-Dist: zope.testing ; extra == 'test'
Requires-Dist: Zope2 ; extra == 'test'
